{
  "decision": "HOLD",
  "confidence": 7,
  "volatility": 13.36,
  "sharpe_ratio": 0.40,
  "reasoning": "The stock's modest weekly return and moderate volatility suggest a decent but not exceptional performance. The company's strong profitability profile and stable business are positives, but the high valuation and debt-to-equity ratio are concerns. The neutral to positive news sentiment and supportive macroeconomic environment do not indicate any major red flags, but they do not provide a strong catalyst for growth either. Therefore, a hold decision is recommended."
}