{"query": "Tata Motors stock trading near 52-week low, is it a value buy?", "similar": [{"title": "Tata Motors shares surged 800% from pandemic low; more upside likely?", "date": "2023-06-22 17:30:00.000", "impact": "-1.93%"}, {"title": "TCS’ Record Date for Interim Dividend Tomorrow; Details Investors Should Know", "date": "2022-07-15 15:28:13.000", "impact": "+0.49%"}, {"title": "Tata Motors, Ashok Leyland, Eicher eye up to 17% gains, charts show", "date": "2022-09-06 13:15:32.000", "impact": "-3.01%"}]}
{"query": "Market Trading Guide: Wipro, Tata Motors among 4 stock recommendations for Thursday", "similar": [{"title": "Key Stocks Under Focus: Oil Companies, Wipro, Tata Power, Max Healthcare & More", "date": "2022-08-19 05:30:00.000", "impact": "-1.79%"}, {"title": "Will metal counters shine going ahead? Here’s what Rajesh Palviya has to say", "date": "2022-11-12 18:13:00.000", "impact": "-1.11%"}, {"title": "Bullish momentum to continue as Fed signals easy policy", "date": "2021-07-15 15:47:57.000", "impact": "+0.14%"}]}
{"query": "Tata Motors teams up with Saraswat Bank to offer competitive interest rates", "similar": [{"title": "Tata Motors ties with Bank of Maharashtra to offer an attractive financing scheme on Passenger Vehicles", "date": "2021-08-17 10:09:00.000", "impact": "-7.47%"}, {"title": "Tata Motors Ties Up With Bandhan Bank For Passenger Vehicle Finance", "date": "2021-12-15 13:18:46.000", "impact": "-5.86%"}, {"title": "Tata Motors partners with Bandhan Bank for passenger vehicle finance", "date": "2021-12-15 14:43:23.000", "impact": "-5.86%"}]}
