{
  "decision": "HOLD",
  "confidence": 6,
  "volatility": 19.37,
  "sharpe_ratio": 0.08,
  "reasoning": "The stock's recent performance is decent, but its risk profile is moderate. The company's financial health is strong, but the high valuation is a concern. The news sentiment is neutral to slightly positive, but the macroeconomic environment is supportive of the insurance industry. Overall, I'm holding the stock due to its strong fundamentals, but I'm cautious about the high valuation and moderate risk profile."
}