{"query": "Hinduja Group’s IndusInd International Holdings acquires 60% in Invesco India", "similar": [{"title": "Hinduja lone bidder for RCap in second auction, offers Rs 9,650 cr", "date": "2023-04-26 17:21:37.000", "impact": "+1.95%"}, {"title": "IndusInd tanks after order against Hinduja Bank resurfaces", "date": "2021-06-03 14:28:00.000", "impact": "-0.56%"}, {"title": "RBI OKs Hinduja hiking IndusInd Bank stake", "date": "2023-02-03 18:03:00.000", "impact": "-0.58%"}]}
{"query": "IndusInd, Invesco sign mutual fund JV", "similar": [{"title": "Divgi TorqTransfer IPO subscribed 12% on Day 1; check latest GMP & other details", "date": "2023-03-01 17:30:00.000", "impact": "+4.30%"}, {"title": "SBI Mutual Fund IPO: SBI to sell 6 percent stake; all you need to know", "date": "2021-12-15 19:13:29", "impact": "-7.47%"}, {"title": "eMudhra collects Rs 124 crore from anchor investors ahead of IPO", "date": "2022-05-19 17:30:00", "impact": "+2.26%"}]}
