{
  "decision": "HOLD",
  "confidence": 6,
  "volatility": 20.4,
  "sharpe_ratio": -0.89,
  "reasoning": "The stock's poor risk-adjusted returns and significant decline in value are concerns. However, the company's strong profitability and manageable debt position are positives. The neutral to positive news sentiment and stable macroeconomic environment also support a hold decision. Overall, the stock's weaknesses in growth prospects and valuation outweigh its strengths, making a hold decision the most prudent choice."
}