{"query": "Cipla arm Cipla Health to buy Ivia Beaute's cosmetics, personal care business for ₹130 crore", "similar": [{"title": "Roche’s antibody cocktail launched in India at ₹59,750/dose", "date": "2021-05-24 12:11:50.000", "impact": "+0.36%"}, {"title": "Board of large-cap pharma company Cipla fixes record date for 250% dividend", "date": "2022-07-27 20:41:37.000", "impact": "+0.14%"}, {"title": "Roche gets Emergency Use nod for Antibody Cocktail for mild-to-moderate Covid-19", "date": "2021-05-05 22:38:43.000", "impact": "-3.94%"}]}
{"query": "Cipla to acquire Ivia Beaute's cosmetics, personal care biz for Rs 130 cr", "similar": [{"title": "Roche’s antibody cocktail launched in India at ₹59,750/dose", "date": "2021-05-24 12:11:50.000", "impact": "+0.36%"}, {"title": "Cipla, Novartis AG ink agreement on diabetes therapy Galvus", "date": "2023-04-11 09:16:00.000", "impact": "+2.10%"}, {"title": "Board of large-cap pharma company Cipla fixes record date for 250% dividend", "date": "2022-07-27 20:41:37.000", "impact": "+0.14%"}]}
{"query": "Cipla subsidiary strengthens presence in cosmetics and personal care", "similar": [{"title": "Cipla: M&A Opportunity Could Be Near-term Trigger", "date": "2021-08-06 11:38:07.000", "impact": "-1.83%"}, {"title": "Concerns arise over Cipla legacy of affordable drugs amid reports of ‘impending takeover’", "date": "2023-08-04 20:31:42.000", "impact": "+2.37%"}, {"title": "Cipla looks to expand its covid-19 portfolio over next two months", "date": "2021-05-16 22:55:30.000", "impact": "+1.29%"}]}
{"query": "Cipla Health acquires Beaute's cosmetics, personal care business for Rs 130 crore", "similar": [{"title": "Roche’s antibody cocktail launched in India at ₹59,750/dose", "date": "2021-05-24 12:11:50.000", "impact": "+0.36%"}, {"title": "Concerns arise over Cipla legacy of affordable drugs amid reports of ‘impending takeover’", "date": "2023-08-04 20:31:42.000", "impact": "+2.37%"}, {"title": "Framework to assess, nudge generic drug makers to expand access to products", "date": "2023-02-15 19:31:51.000", "impact": "-0.99%"}]}
{"query": "Cipla Health to acquire distribution, marketing business undertaking of Ivia Beaute’s cosmetics and personal care business", "similar": [{"title": "Roche’s antibody cocktail launched in India at ₹59,750/dose", "date": "2021-05-24 12:11:50.000", "impact": "+0.36%"}, {"title": "Cipla, Novartis AG ink agreement on diabetes therapy Galvus", "date": "2023-04-11 09:16:00.000", "impact": "+2.10%"}, {"title": "Roche gets Emergency Use nod for Antibody Cocktail for mild-to-moderate Covid-19", "date": "2021-05-05 22:38:43.000", "impact": "-3.94%"}]}
{"query": "Cipla gets Rs 1.83 crore penalty for claiming inadmissible transitional credit on education cess", "similar": [{"title": "RBI imposes monetary penalty of Rs 30 lakh on ICICI Bank and Rs 1.8 crore on PNB", "date": "2021-12-15 20:34:00.000", "impact": "-3.91%"}, {"title": "No immediate change to products, Citi tells customers | The Financial Express", "date": "2022-04-11 09:52:49.000", "impact": "+0.45%"}, {"title": "RBI penalises J&K Bank, Bank of Maharashtra, Axis Bank", "date": "2023-06-23 20:54:00.000", "impact": "-1.67%"}]}
{"query": "Cipla Health signs agreement, strengthens beauty play with Ivia's brands", "similar": [{"title": "Cipla shares edge higher on large exchange volumes, hopes of better sales", "date": "2023-04-12 10:40:16.000", "impact": "+2.10%"}, {"title": "Cipla builds on its diabetes portfolio with Galvus agreement", "date": "2023-05-17 14:55:01.000", "impact": "-2.53%"}, {"title": "Cipla inks licensing pact with Novartis to manufacture, mkt diabetes drug", "date": "2023-04-10 20:58:31.000", "impact": "+2.10%"}]}
