{"query": "ONGC, Indraprastha Gas among 5 stocks that may gain from rising crude oil prices", "similar": [{"title": "ONGC surges 6%, hits 22-month high on improved outlook; Oil India up 7%", "date": "2021-09-21 13:22:00.000", "impact": "+8.84%"}, {"title": "ONGC is regaining lost ground: Why it is stock pick of the week", "date": "2021-03-30 10:26:00.000", "impact": "+0.29%"}, {"title": "ONGC share in India’s oil, gas production rises; not a ‘drag’ anymore", "date": "2021-08-09 22:37:42.000", "impact": "+0.09%"}]}
{"query": "bp simplifies organisational structure and announces executive team changes | News and insights | Home", "similar": [{"title": "Infosys, bp ink MoU on application service | The Financial Express", "date": "2023-05-17 03:10:00.000", "impact": "-0.36%"}, {"title": "Raj Kumar Dubey takes over as BPCL’s Director HR", "date": "2023-05-01 20:49:00.000", "impact": "+0.50%"}, {"title": "HCL Technologies helps digitise BP’s workplace in multi-year deal", "date": "2021-07-09 16:15:00.000", "impact": "-1.05%"}]}
{"query": "Osaka Gas, Sumitomo, and JOIN to Invest in Expanding City Gas Distribution Business in India", "similar": [{"title": "IGGL achieves 42.94 per cent physical progress, Rs 1556.46 crore capital expenditure", "date": "2022-09-22 14:00:00.000", "impact": "-2.65%"}, {"title": "IOC to invest Rs 7,000 cr in city gas after it secures 33% market areas", "date": "2022-01-16 17:01:00.000", "impact": "+1.77%"}, {"title": "Huge business potential in India, says Maruti Suzuki MD Hisashi Takeuchi", "date": "2022-10-30 15:39:00.000", "impact": "+0.53%"}]}
