{"query": "Adani Ports and Special Economic Zone Shares Decline 2.58% Amid Volume Surge", "similar": [{"title": "Hindenburg effect fades: Adani Ports shares zoom 10% in early trade", "date": "2023-01-30 17:30:00.000", "impact": "-19.54%"}, {"title": "Adani Ports SEZ Sept quarter profit jumps 62% as cargo volumes surge", "date": "2022-11-01 16:56:08.000", "impact": "+4.72%"}, {"title": "Why Adani Ports Share Dropped 9% on Monday, and What Next?", "date": "2021-06-15 08:22:00.000", "impact": "-8.13%"}]}
