{
  "decision": "HOLD",
  "confidence": 7,
  "volatility": 8.72,
  "sharpe_ratio": 0.77,
  "reasoning": "ICICIBANK's decent weekly return and moderate volatility suggest a stable performance. However, the high forward P/E ratio raises concerns about overvaluation. The company's strong financial health, decent dividend yield, and no debt-to-equity ratio are positives. Considering the macroeconomic environment, the banking sector is expected to perform well, but ICICIBANK's valuation is a concern, leading me to recommend a HOLD decision."
}