{
  "decision": "BUY",
  "confidence": 8,
  "volatility": 19.08,
  "sharpe_ratio": 0.36,
  "reasoning": "The stock's decent performance, with a moderate return of 1.74%, is accompanied by a reasonable valuation with a trailing P/E of 21.23. The company's strong profitability profile, with a high ROE of 14.57%, and absence of debt indicate a robust balance sheet. The positive news sentiment, with the upcoming IPO of HDB Financial Services and significant buying by mutual funds, suggests a potential upside for the stock."
}