{"query": "Apollo Hospitals Enterprise Ltd. Reports Revision in Stock Score Amid Recent Market Fluctuations", "similar": [{"title": "Apollo Hospitals, IOC in action after NIFTY rejig", "date": "2022-02-25 09:31:00.000", "impact": "+3.63%"}, {"title": "Technical Analysis: Apollo Pipes, Axis Bank and Sunteck Realty", "date": "2023-07-29 19:04:12.000", "impact": "+3.95%"}, {"title": "Key Stocks to Track on Sept 13: TCS, Gujarat Apollo, HDFC Life & More", "date": "2022-09-13 05:30:00.000", "impact": "-4.32%"}]}
{"query": "These 5 stocks are sharply up in a falling market, here’s why…", "similar": [{"title": "Kunj Bansal on why a two-player market may be bad for Bharti Airtel", "date": "2021-09-10 09:01:00.000", "impact": "-6.15%"}, {"title": "Bajaj Fin, Asian Paints, Adani among consistent performers", "date": "2022-01-04 06:00:00.000", "impact": "-0.33%"}, {"title": "Axis Bank, SBI: 5 bank stocks that may give up to 10% return in a month", "date": "2021-11-25 11:51:00.000", "impact": "+1.62%"}]}
{"query": "HMPV Virus 2025: Which Indian Stocks Could be the New Winners?", "similar": [{"title": "Jefferies Downgrades Tech Mahindra, TCS On Margin Woes; Hikes Infosys, HCL Tech Price Targets", "date": "2021-07-02 12:53:48.000", "impact": "+8.28%"}, {"title": "HCL Tech, Navin Fluorine, Bata India And More: Axis Securities’ Top Picks For January", "date": "2022-01-05 07:46:32.000", "impact": "-0.33%"}, {"title": "Vinit Bolinjkar on why NBFC stocks are back in demand & what are the top picks", "date": "2022-12-04 10:35:00.000", "impact": "+2.32%"}]}
{"query": "Microsoft inks strategic partnerships to make India’s core sectors AI-first - Microsoft Stories India", "similar": [{"title": "To AI or not no longer a question: IT majors already using GenAI for several tasks", "date": "2023-08-01 16:14:00.000", "impact": "-6.74%"}, {"title": "Big brothers leading the way; Happiest Minds seeing growth in the market: MD", "date": "2022-06-28 12:54:00.000", "impact": "-2.93%"}, {"title": "TCS wins 2022 Microsoft Supplier of the Year award", "date": "2022-10-03 17:50:05.000", "impact": "+0.21%"}]}
