{"query": "HDFC Bank, Bajaj Finance: 5 BFSI stock picks ahead of Q3 results, target prices", "similar": [{"title": "HDFC twins gain up to 3% after they fix July 13 as record date for merger", "date": "2023-07-03 10:16:07.000", "impact": "-3.04%"}, {"title": "Why is HDFC Bank & Bajaj Finance divergent in a bull market? Hemang Jani answers", "date": "2022-02-16 14:40:00.000", "impact": "+1.50%"}, {"title": "Brokerages Expect HDFC Bank To Return Up To 32%; Resumption Of Credit Card Issuance To Aid Margin Recovery", "date": "2022-01-05 12:56:58.000", "impact": "+4.41%"}]}
{"query": "Buy HDFC Bank, target price Rs 1748: Motilal Oswal Financial Services", "similar": [{"title": "HDFC Bank - Key Overhang Addressed; Growth Trend To Revive: Motilal Oswal", "date": "2021-09-21 09:34:47.000", "impact": "+2.40%"}, {"title": "ICICI Securities sees over 40% upside potential on this banking stock", "date": "2022-06-05 18:07:44.000", "impact": "-2.12%"}, {"title": "Hemang Jani on why FIIs are selling HDFC Bank and not Bajaj Finance", "date": "2022-04-21 12:39:00.000", "impact": "-4.46%"}]}
