{"query": "Nestle India Share Price Highlights: Nestle India Stock Performance Overview", "similar": [{"title": "Brokerages hold mixed views on Nestle", "date": "2021-04-22 07:06:00.000", "impact": "-3.34%"}, {"title": "Nestle India Shares Trade Ex-Dividend; Key Details Investors Must Know", "date": "2023-04-21 12:47:27.000", "impact": "+4.63%"}, {"title": "Nestle India net profit rises 10.68% to ₹538.5 crore in June quarter", "date": "2021-07-28 22:39:47.000", "impact": "-2.04%"}]}
{"query": "Nestle India Ltd gains for third straight session", "similar": [{"title": "Nestle India net profit up 24.7% in March quarter", "date": "2023-04-25 12:07:41.000", "impact": "+6.15%"}, {"title": "Nestle India net profit rises 10.68% to ₹538.5 crore in June quarter", "date": "2021-07-28 22:39:47.000", "impact": "-2.04%"}, {"title": "Inflation in food, commodity to stay for a while, cause of concern: Nestle India CMD Suresh Narayanan", "date": "2022-02-17 22:53:00.000", "impact": "+1.66%"}]}
