{
  "decision": "BUY",
  "confidence": 8,
  "volatility": 21.2,
  "sharpe_ratio": 0.35,
  "reasoning": "The stock's strong weekly performance, with a return of 1.85%, and a positive news sentiment with multiple announcements indicating significant investments and expansion plans, suggest a potential upward trend. Although the company's financial health is mixed, with low profitability metrics and high debt-to-equity ratio, the attractive valuation and high dividend yield are strengths. The macroeconomic environment, with a growing services sector and improving consumer behavior, also supports the stock's growth potential."
}