{"query": "bajaj finance quarterly result for q1 2025", "similar": [{"title": "Bajaj Finance Results Preview | Net profit to soar 75% on strong loan growth", "date": "2022-04-22 11:33:18.000", "impact": "-2.13%"}, {"title": "Bajaj Auto reports 2% decline in total June sales to 340,981 units", "date": "2023-07-03 10:39:17.000", "impact": "+6.45%"}, {"title": "Bajaj Finance Shares Fall As Analysts See Extended Lockdowns, Third Covid-19 Wave As Risks", "date": "2021-06-07 14:11:40.000", "impact": "+5.52%"}]}
