{"query": "Adani Group stocks down as much as 2%: Here's why… - Market News", "similar": [{"title": "Adani Group Rejects OCCRP Allegations On Stock Manipulation", "date": "2023-08-31 19:28:31.000", "impact": "-3.92%"}, {"title": "Sebi seeks info on ratings of Adani firms’ loans, says report; investors lose Rs 51,000 cr today", "date": "2023-02-22 17:30:00.000", "impact": "-20.26%"}, {"title": "Deloitte resignation effect: Adani group shares end in the red", "date": "2023-08-14 22:13:20.000", "impact": "+3.93%"}]}
{"query": "Adani Enterprises, Adani Ports to Adani Total Gas: Five Adani group shares to trade ex-dividend today", "similar": [{"title": "Most Adani Group stocks rise on GQG’s additional stake buying report, jump up to 5%", "date": "2023-06-28 17:30:00.000", "impact": "+8.05%"}, {"title": "Adani Enterprises, Adani Ports, Adani Green shares drop as Sebi seeks extension to probe Hindenburg allegations", "date": "2023-08-14 17:30:00.000", "impact": "+3.93%"}, {"title": "Adani Ports shares rise, near Rs 700 level, as Adani group firm looks to pay $130 million debt early", "date": "2023-05-09 17:30:00.000", "impact": "+2.31%"}]}
{"query": "Adani Ports, Adani Enterprises, Other Group Stocks Rise As Group CFO Unveils $100-Billion Capex Plan", "similar": [{"title": "Adani Power, Adani Green, Adani Total, Adani Wilmar & Adani Transmission: 5 Adani stocks where MF upped stakes in Nov", "date": "2022-12-15 17:30:00.000", "impact": "-0.41%"}, {"title": "Adani Ports shares rise, near Rs 700 level, as Adani group firm looks to pay $130 million debt early", "date": "2023-05-09 17:30:00.000", "impact": "+2.31%"}, {"title": "GQG Partners trims its stake in HDFC AMC from 5.33% to 2.76%", "date": "2023-03-17 23:08:49.000", "impact": "-2.11%"}]}
{"query": "‘Investors from US, Middle East interested…’: Adani Airport Holdings may raise $1 billion in equity; firs", "similar": [{"title": "Adani group units in talks to tap local bond market, sources", "date": "2023-08-11 19:09:24.000", "impact": "-0.45%"}, {"title": "Neither macro fundamentals nor country’s image impacted by Adani saga: FM", "date": "2023-02-05 15:45:18", "impact": "-44.32%"}, {"title": "Adani Enterprises FPO’s anchor book gets 1.5x bids", "date": "2023-01-26 00:24:57", "impact": "-19.80%"}]}
