{"query": "Stocks to buy today: Infosys, Biocon among top 7 trading ideas for 12 June 2025", "similar": [{"title": "TCS to Infosys to Tech Mahindra — experts suggest top 5 IT shares to buy on dips", "date": "2021-04-14 10:02:26.000", "impact": "-8.16%"}, {"title": "Key Stocks in Focus on Dec 8: Infosys, Eicher, BLS International, Lumax & More", "date": "2022-12-08 05:30:00.000", "impact": "-4.19%"}, {"title": "Why Rajat Sharma is bullish on FMCG stocks & betting on Infosys", "date": "2022-07-28 11:56:00.000", "impact": "+4.70%"}]}
{"query": "Infosys allots 59,314 equity shares under ESOP", "similar": [{"title": "ITC allots 25 lakh equity shares under ESOS; Stock dips 2%", "date": "2021-02-26 18:24:00.000", "impact": "-3.22%"}, {"title": "Axis Bank board allots 94,821 equity shares under ESOP scheme", "date": "2021-05-25 15:00:00.000", "impact": "+3.57%"}, {"title": "Axis Bank allots 1.5 lakh equity shares under ESOP; Stock trades higher", "date": "2021-03-31 15:28:00.000", "impact": "+2.84%"}]}
{"query": "Infosys Shares Rally As DGGI Closes Rs 32,400 Crore Tax Proceedings", "similar": [{"title": "Infy’s 7% drop hints at further weakness for tech counters", "date": "2022-04-19 05:54:00.000", "impact": "-1.25%"}, {"title": "SD Shibulal buys Rs 100-crore Infosys shares from wife for a third time this month", "date": "2021-05-28 11:38:00.000", "impact": "+3.57%"}, {"title": "S D Shibulal buys Infosys shares worth Rs 100 cr from wife Kumari Shibulal", "date": "2021-05-25 10:23:38.000", "impact": "+3.57%"}]}
{"query": "Infosys to announce Q1 FY26 results on July 23", "similar": [{"title": "Bad News For Infosys Employees! Company Defers Salary Hikes - News18", "date": "2023-07-12 15:26:08.000", "impact": "+6.69%"}, {"title": "Infosys hits record high after reporting fastest revenue growth in a decade", "date": "2021-07-15 19:58:10.000", "impact": "-0.96%"}, {"title": "Infosys, Tata Steel, ICICI Bank, MCX in spotlight", "date": "2022-04-13 08:52:00.000", "impact": "-3.61%"}]}
{"query": "Infosys CEO Salil Parekh gets a 22% hike in annual remuneration, annual report shows", "similar": [{"title": "Southern Slice | India’s IT Industry has Only Two Emotions for Infosys CEO’s 88% Raise - Heartburn and Hope", "date": "2022-05-28 12:07:52.000", "impact": "+0.43%"}, {"title": "Infosys CEO To Get Rs 80-Crore Salary: Revenue to Return, How Parekh Transformed Company", "date": "2022-05-31 17:20:19.000", "impact": "+2.33%"}, {"title": "Infosys CEO Salil Parekh gets a huge salary hike, his compensation jumps 88 per cent", "date": "2022-05-26 17:30:00.000", "impact": "+0.43%"}]}
