{
  "decision": "HOLD",
  "confidence": 6,
  "volatility": 23.89,
  "sharpe_ratio": 0.98,
  "reasoning": "The stock's strong weekly performance and relatively low risk as indicated by the Sharpe Ratio are positives. However, the company's high debt levels and negative revenue growth are concerns. Additionally, the macroeconomic environment suggests a mixed outlook for the industry, with some positive trends in agriculture and services, but also rising interest rates and trade deficits. Overall, I would hold the stock for now, but closely monitor its performance and adjust my decision as needed."
}