{"query": "India, Sri Lanka working to link power grids via undersea transmission line", "similar": [{"title": "Power Grid becomes top bidder for 2 projects in Chhattisgarh, shares head north", "date": "2023-03-06 09:46:08.000", "impact": "+1.14%"}, {"title": "PowerGrid, Tata Power, Bharat Electronics in focus", "date": "2023-03-01 09:04:39.000", "impact": "+2.61%"}, {"title": "State-run PGCIL wins two power transmission projects in Rajasthan", "date": "2021-01-30 15:56:00.000", "impact": "-5.14%"}]}
{"query": "17th annual conference on Power Transmission in India | February 27-28, 2024 | The Leela Ambience", "similar": [{"title": "GE Grid Solutions bags orders of transformers, reactors from Power Grid Corp of India", "date": "2021-07-21 15:49:01.000", "impact": "-0.36%"}, {"title": "K E C International secures orders worth Rs 945 cr", "date": "2022-04-05 16:11:00.000", "impact": "+2.92%"}, {"title": "Power Grid receives LoI for transmission system project in Rajasthan", "date": "2021-02-01 19:13:00.000", "impact": "+12.28%"}]}
{"query": "Power sector to see ₹17 L cr investments in 5-7 yrs: Power and renewable energy minister RK Singh", "similar": [{"title": "Reliance Industries signs MoU with Govt. of Gujarat", "date": "2022-01-13 16:26:00.000", "impact": "+0.24%"}, {"title": "Jefferies is bullish on this Maharatna PSU stock, sees new 52-week-high", "date": "2022-09-23 18:21:03.000", "impact": "-14.16%"}, {"title": "Board of Maharatna company announces record date for dividend for FY 2021-22", "date": "2022-08-07 21:11:04.000", "impact": "+4.00%"}]}
{"query": "Power Sector: Is it heading towards another collapse? Bernstein answers", "similar": [{"title": "Coal India suspends e-auction as coal crisis deepens, metal makers face a shortage", "date": "2021-10-14 19:45:00.000", "impact": "+7.71%"}, {"title": "NITI Aayog to develop net zero greenhouse gas emissions roadmap for NTPC", "date": "2022-07-21 15:59:36.000", "impact": "-0.17%"}, {"title": "This is still a sell-on-rise market; 15,500 is a positional target for Nifty: Rahul Sharma", "date": "2022-05-10 16:48:00.000", "impact": "-1.13%"}]}
