{"query": "TCS Dividend 2025, Q4 results FY25 date: Another cash reward! Quarterly earnings announcement schedule of Tata Group company", "similar": [{"title": "TCS to trade ex-dividend on Monday: Record and payment dates here", "date": "2023-01-16 06:35:20.000", "impact": "+1.39%"}, {"title": "TCS Shares Surge Ahead Of December Quarter Results; What Investors Need to Know", "date": "2023-01-09 13:57:15.000", "impact": "+4.51%"}, {"title": "TCS down 1% as stock trades ex-dividend", "date": "2023-06-15 09:53:12.000", "impact": "-1.25%"}]}
