{"query": "Dividend Stocks: Coal India, HCl Tech, ONGC, Bank of Baroda among top 10 picks by Religare Broking", "similar": [{"title": "HCL Tech, Navin Fluorine, Bata India And More: Axis Securities’ Top Picks For January", "date": "2022-01-05 07:46:32.000", "impact": "-1.96%"}, {"title": "These stocks are expected to return between 11% and 26%", "date": "2022-08-30 06:23:00.000", "impact": "+1.30%"}, {"title": "Coal India, APL Apollo Tubes, CCL Products And More - Top Stock Picks For August By Axis Securities", "date": "2022-08-03 12:23:24.000", "impact": "+0.39%"}]}
{"query": "HCLTech to acquire France-based software provider Zeenea: Five things you need to know", "similar": [{"title": "HCL Technologies signs 5-year agreement with Airbus, plans expansion", "date": "2021-02-04 21:13:00.000", "impact": "+2.95%"}, {"title": "HCL Technologies enters into application deal with Euroclear Group", "date": "2021-11-16 16:30:00.000", "impact": "-4.34%"}, {"title": "Vodafone Germany, Tech Mahindra deepen partnership for enhanced service", "date": "2023-02-23 18:03:27.000", "impact": "-1.32%"}]}
{"query": "Sensex, Nifty rise a day after market meltdown tracking Asian peers", "similar": [{"title": "HCL Tech, MindTree to ITI — experts recommend ‘buy’ on these tech stocks", "date": "2021-07-01 08:32:12.000", "impact": "-1.53%"}, {"title": "EMERGING MARKETS-Asian FX firm as dollar slips; Indian shares rebound on ICICI Bank result", "date": "2021-04-26 05:30:00.000", "impact": "-4.37%"}, {"title": "Wipro’s shares dip, HCLTech shines as IT sector braces for slowdown: Report", "date": "2022-10-13 11:39:41.000", "impact": "+6.41%"}]}
