{
  "decision": "BUY",
  "confidence": 8,
  "volatility": 11.04,
  "sharpe_ratio": -0.88,
  "reasoning": "The stock's fundamentals are strong, with high gross margins and EBITDA margins, and a respectable ROE. The news sentiment is positive, with several notable events that could drive growth and increase investor confidence. Although the stock's recent performance was disappointing, the macroeconomic environment is supportive, with a growing services sector, low inflation, and a stable repo rate. Therefore, I believe the stock is a buying opportunity."
}