{
  "metrics": {
    "symbol": "AXISBANK.NS",
    "companyName": "Axis Bank Limited",
    "sector": "Financial Services",
    "industry": "Banks - Regional",
    "marketCap": 3787502649344,
    "trailingPE": 13.537301,
    "forwardPE": null,
    "bookValue": 575.849,
    "dividendYield": 0.08,
    "returnOnEquity": 0.16324,
    "ebitdaMargins": 0.0,
    "grossMargins": 0.0,
    "profitMargins": 0.36571,
    "revenueGrowth": 0.866,
    "earningsGrowth": -0.066,
    "debtToEquity": null
  },
  "balance_sheet": {
    "2025-03-31": {
      "Treasury Shares Number": "0.0",
      "Ordinary Shares Number": "3097369066.0",
      "Share Issued": "3097369066.0",
      "Net Debt": "1179880500000.0",
      "Total Debt": "2206867500000.0",
      "Tangible Book Value": "1869462500000.0",
      "Invested Capital": "4079222400000.0",
      "Net Tangible Assets": "1869462500000.0",
      "Common Stock Equity": "1872354900000.0",
      "Total Capitalization": "4079222400000.0",
      "Total Equity Gross Minority Interest": "1878706200000.0",
      "Minority Interest": "6351300000.0",
      "Stockholders Equity": "1872354900000.0",
      "Other Equity Interest": "11826600000.0",
      "Retained Earnings": "0.0",
      "Additional Paid In Capital": "0.0",
      "Capital Stock": "6194700000.0",
      "Common Stock": "6194700000.0",
      "Total Liabilities Net Minority Interest": "14690919900000.0",
      "Long Term Debt And Capital Lease Obligation": "2206867500000.0",
      "Payables": "0.0",
      "Other Payable": "0.0",
      "Accounts Payable": "0.0",
      "Total Assets": "16569626100000.0",
      "Investments And Advances": "3966850700000.0",
      "Investmentin Financial Assets": "3966850700000.0",
      "Available For Sale Securities": "0.0",
      "Long Term Equity Investment": "0.0",
      "Investmentsin Associatesat Cost": "0.0",
      "Goodwill And Other Intangible Assets": "2892400000.0",
      "Goodwill": "2892400000.0",
      "Net PPE": "64920800000.0",
      "Accumulated Depreciation": "0.0",
      "Gross PPE": "0.0",
      "Construction In Progress": "0.0",
      "Other Properties": "0.0",
      "Buildings And Improvements": "0.0",
      "Prepaid Assets": "0.0",
      "Receivables": "0.0",
      "Cash And Cash Equivalents": "1026987000000.0",
      "Cash Equivalents": "0.0",
      "Cash Financial": "736384400000.0",
      "Cash Cash Equivalents And Federal Funds Sold": "1026987000000.0"
    },
    "2024-12-31": {
      "Treasury Shares Number": "0.0",
      "Ordinary Shares Number": "3095171531.0",
      "Share Issued": "3095171531.0",
      "Net Debt": "1374807700000.0",
      "Total Debt": "2250208100000.0",
      "Tangible Book Value": "1791837400000.0",
      "Invested Capital": "4044937900000.0",
      "Net Tangible Assets": "1791837400000.0",
      "Common Stock Equity": "1794729800000.0",
      "Total Capitalization": "4044937900000.0",
      "Total Equity Gross Minority Interest": "1800741400000.0",
      "Minority Interest": "6011600000.0",
      "Stockholders Equity": "1794729800000.0",
      "Other Equity Interest": "10943800000.0",
      "Retained Earnings": "0.0",
      "Additional Paid In Capital": "0.0",
      "Capital Stock": "6190300000.0",
      "Common Stock": "6190300000.0",
      "Total Liabilities Net Minority Interest": "13917197100000.0",
      "Long Term Debt And Capital Lease Obligation": "2250208100000.0",
      "Payables": "0.0",
      "Other Payable": "0.0",
      "Accounts Payable": "0.0",
      "Total Assets": "15717938500000.0",
      "Investments And Advances": "3538140600000.0",
      "Investmentin Financial Assets": "3538140600000.0",
      "Available For Sale Securities": "0.0",
      "Long Term Equity Investment": "0.0",
      "Investmentsin Associatesat Cost": "0.0",
      "Goodwill And Other Intangible Assets": "2892400000.0",
      "Goodwill": "2892400000.0",
      "Net PPE": "62691800000.0",
      "Accumulated Depreciation": "0.0",
      "Gross PPE": "0.0",
      "Construction In Progress": "0.0",
      "Other Properties": "0.0",
      "Buildings And Improvements": "0.0",
      "Prepaid Assets": "0.0",
      "Receivables": "0.0",
      "Cash And Cash Equivalents": "875400400000.0",
      "Cash Equivalents": "0.0",
      "Cash Financial": "563220800000.0",
      "Cash Cash Equivalents And Federal Funds Sold": "875400400000.0"
    },
    "2024-09-30": {
      "Treasury Shares Number": "0.0",
      "Ordinary Shares Number": "3093254378.0",
      "Share Issued": "3093254378.0",
      "Net Debt": "1359981500000.0",
      "Total Debt": "2252174600000.0",
      "Tangible Book Value": "1721327600000.0",
      "Invested Capital": "3976394600000.0",
      "Net Tangible Assets": "1721327600000.0",
      "Common Stock Equity": "1724220000000.0",
      "Total Capitalization": "3976394600000.0",
      "Total Equity Gross Minority Interest": "1729865500000.0",
      "Minority Interest": "5645500000.0",
      "Stockholders Equity": "1724220000000.0",
      "Other Equity Interest": "10193800000.0",
      "Retained Earnings": "0.0",
      "Additional Paid In Capital": "0.0",
      "Capital Stock": "6186500000.0",
      "Common Stock": "6186500000.0",
      "Total Liabilities Net Minority Interest": "13792358500000.0",
      "Long Term Debt And Capital Lease Obligation": "2252174600000.0",
      "Payables": "0.0",
      "Other Payable": "0.0",
      "Accounts Payable": "0.0",
      "Total Assets": "15522224000000.0",
      "Investments And Advances": "3495702000000.0",
      "Investmentin Financial Assets": "3495702000000.0",
      "Available For Sale Securities": "0.0",
      "Long Term Equity Investment": "0.0",
      "Investmentsin Associatesat Cost": "0.0",
      "Goodwill And Other Intangible Assets": "2892400000.0",
      "Goodwill": "2892400000.0",
      "Net PPE": "61043800000.0",
      "Accumulated Depreciation": "0.0",
      "Gross PPE": "0.0",
      "Construction In Progress": "0.0",
      "Other Properties": "0.0",
      "Buildings And Improvements": "0.0",
      "Prepaid Assets": "0.0",
      "Receivables": "0.0",
      "Cash And Cash Equivalents": "892193100000.0",
      "Cash Equivalents": "0.0",
      "Cash Financial": "621182000000.0",
      "Cash Cash Equivalents And Federal Funds Sold": "892193100000.0"
    },
    "2024-06-30": {
      "Treasury Shares Number": "0.0",
      "Ordinary Shares Number": "3090246466.0",
      "Share Issued": "3090246466.0",
      "Net Debt": "1136234800000.0",
      "Total Debt": "2240367100000.0",
      "Tangible Book Value": "1646498200000.0",
      "Invested Capital": "3889757700000.0",
      "Net Tangible Assets": "1646498200000.0",
      "Common Stock Equity": "1649390600000.0",
      "Total Capitalization": "3889757700000.0",
      "Total Equity Gross Minority Interest": "1654692000000.0",
      "Minority Interest": "5301400000.0",
      "Stockholders Equity": "1649390600000.0",
      "Other Equity Interest": "9392300000.0",
      "Retained Earnings": "0.0",
      "Additional Paid In Capital": "0.0",
      "Capital Stock": "6180500000.0",
      "Common Stock": "6180500000.0",
      "Total Liabilities Net Minority Interest": "13480063100000.0",
      "Long Term Debt And Capital Lease Obligation": "2240367100000.0",
      "Payables": "0.0",
      "Other Payable": "0.0",
      "Accounts Payable": "0.0",
      "Total Assets": "15134755100000.0",
      "Investments And Advances": "3173772800000.0",
      "Investmentin Financial Assets": "3173772800000.0",
      "Available For Sale Securities": "0.0",
      "Long Term Equity Investment": "0.0",
      "Investmentsin Associatesat Cost": "0.0",
      "Goodwill And Other Intangible Assets": "2892400000.0",
      "Goodwill": "2892400000.0",
      "Net PPE": "60090600000.0",
      "Accumulated Depreciation": "0.0",
      "Gross PPE": "0.0",
      "Construction In Progress": "0.0",
      "Other Properties": "0.0",
      "Buildings And Improvements": "0.0",
      "Prepaid Assets": "0.0",
      "Receivables": "0.0",
      "Cash And Cash Equivalents": "1104132300000.0",
      "Cash Equivalents": "0.0",
      "Cash Financial": "632904500000.0",
      "Cash Cash Equivalents And Federal Funds Sold": "1104132300000.0"
    },
    "2024-03-31": {
      "Treasury Shares Number": "0.0",
      "Ordinary Shares Number": "3086570375.0",
      "Share Issued": "3086570375.0",
      "Net Debt": "901492700000.0",
      "Total Debt": "2281995500000.0",
      "Tangible Book Value": "1563657400000.0",
      "Invested Capital": "3852230700000.0",
      "Net Tangible Assets": "1563657400000.0",
      "Common Stock Equity": "1570235200000.0",
      "Total Capitalization": "3852230700000.0",
      "Total Equity Gross Minority Interest": "1575229600000.0",
      "Minority Interest": "4994400000.0",
      "Stockholders Equity": "1570235200000.0",
      "Other Equity Interest": "8944900000.0",
      "Retained Earnings": "652811700000.0",
      "Additional Paid In Capital": "525400000000.0",
      "Capital Stock": "6173100000.0",
      "Common Stock": "6173100000.0",
      "Total Liabilities Net Minority Interest": "13607155700000.0",
      "Long Term Debt And Capital Lease Obligation": "2281995500000.0",
      "Payables": "103721100000.0",
      "Other Payable": "67138900000.0",
      "Accounts Payable": "36582200000.0",
      "Total Assets": "15182385300000.0",
      "Investments And Advances": "2287663000000.0",
      "Investmentin Financial Assets": "2282023900000.0",
      "Available For Sale Securities": "70166100000.0",
      "Long Term Equity Investment": "5639100000.0",
      "Investmentsin Associatesat Cost": "5639100000.0",
      "Goodwill And Other Intangible Assets": "6577800000.0",
      "Goodwill": "6577800000.0",
      "Net PPE": "58375600000.0",
      "Accumulated Depreciation": "-206452000000.0",
      "Gross PPE": "264827600000.0",
      "Construction In Progress": "2669000000.0",
      "Other Properties": "260062600000.0",
      "Buildings And Improvements": "2096000000.0",
      "Prepaid Assets": "1963100000.0",
      "Receivables": "281508900000.0",
      "Cash And Cash Equivalents": "1380502800000.0",
      "Cash Equivalents": "131584600000.0",
      "Cash Financial": "96348100000.0",
      "Cash Cash Equivalents And Federal Funds Sold": "1380502800000.0"
    },
    "2023-12-31": {
      "Treasury Shares Number": "0.0",
      "Ordinary Shares Number": "0.0",
      "Share Issued": "0.0",
      "Net Debt": "0.0",
      "Total Debt": "0.0",
      "Tangible Book Value": "0.0",
      "Invested Capital": "0.0",
      "Net Tangible Assets": "0.0",
      "Common Stock Equity": "0.0",
      "Total Capitalization": "0.0",
      "Total Equity Gross Minority Interest": "0.0",
      "Minority Interest": "0.0",
      "Stockholders Equity": "0.0",
      "Other Equity Interest": "0.0",
      "Retained Earnings": "0.0",
      "Additional Paid In Capital": "0.0",
      "Capital Stock": "0.0",
      "Common Stock": "0.0",
      "Total Liabilities Net Minority Interest": "0.0",
      "Long Term Debt And Capital Lease Obligation": "0.0",
      "Payables": "0.0",
      "Other Payable": "0.0",
      "Accounts Payable": "0.0",
      "Total Assets": "0.0",
      "Investments And Advances": "0.0",
      "Investmentin Financial Assets": "0.0",
      "Available For Sale Securities": "0.0",
      "Long Term Equity Investment": "0.0",
      "Investmentsin Associatesat Cost": "0.0",
      "Goodwill And Other Intangible Assets": "0.0",
      "Goodwill": "0.0",
      "Net PPE": "0.0",
      "Accumulated Depreciation": "0.0",
      "Gross PPE": "0.0",
      "Construction In Progress": "0.0",
      "Other Properties": "0.0",
      "Buildings And Improvements": "0.0",
      "Prepaid Assets": "0.0",
      "Receivables": "0.0",
      "Cash And Cash Equivalents": "0.0",
      "Cash Equivalents": "0.0",
      "Cash Financial": "0.0",
      "Cash Cash Equivalents And Federal Funds Sold": "0.0"
    }
  },
  "income_stmt": {
    "2025-03-31": {
      "Tax Effect Of Unusual Items": "0.0",
      "Tax Rate For Calcs": "0.243064",
      "Total Unusual Items": "0.0",
      "Total Unusual Items Excluding Goodwill": "0.0",
      "Net Income From Continuing Operation Net Minority Interest": "74751300000.0",
      "Net Interest Income": "143316100000.0",
      "Interest Expense": "181207100000.0",
      "Interest Income": "324523200000.0",
      "Normalized Income": "74751300000.0",
      "Net Income From Continuing And Discontinued Operation": "74751300000.0",
      "Diluted Average Shares": "0.0",
      "Basic Average Shares": "0.0",
      "Diluted EPS": "0.0",
      "Basic EPS": "0.0",
      "Diluted NI Availto Com Stockholders": "74751300000.0",
      "Net Income Common Stockholders": "74751300000.0",
      "Net Income": "74751300000.0",
      "Minority Interests": "-339700000.0",
      "Net Income Including Noncontrolling Interests": "75091000000.0",
      "Net Income Extraordinary": "0.0",
      "Net Income Continuous Operations": "75091000000.0",
      "Tax Provision": "24050600000.0",
      "Pretax Income": "98947700000.0",
      "Special Income Charges": "0.0",
      "Operating Expense": "103922800000.0",
      "Other Operating Expenses": "70522800000.0",
      "Total Revenue": "218373300000.0",
      "Operating Revenue": "218373300000.0"
    },
    "2024-12-31": {
      "Tax Effect Of Unusual Items": "0.0",
      "Tax Rate For Calcs": "0.249108",
      "Total Unusual Items": "0.0",
      "Total Unusual Items Excluding Goodwill": "0.0",
      "Net Income From Continuing Operation Net Minority Interest": "67422900000.0",
      "Net Interest Income": "141225200000.0",
      "Interest Expense": "180396800000.0",
      "Interest Income": "321622000000.0",
      "Normalized Income": "67422900000.0",
      "Net Income From Continuing And Discontinued Operation": "67422900000.0",
      "Diluted Average Shares": "3114221709.0",
      "Basic Average Shares": "3094212942.0",
      "Diluted EPS": "21.65",
      "Basic EPS": "21.79",
      "Diluted NI Availto Com Stockholders": "67422900000.0",
      "Net Income Common Stockholders": "67422900000.0",
      "Net Income": "67422900000.0",
      "Minority Interests": "-366200000.0",
      "Net Income Including Noncontrolling Interests": "67789100000.0",
      "Net Income Extraordinary": "0.0",
      "Net Income Continuous Operations": "67789100000.0",
      "Tax Provision": "22436600000.0",
      "Pretax Income": "90067600000.0",
      "Special Income Charges": "0.0",
      "Operating Expense": "96727500000.0",
      "Other Operating Expenses": "63189300000.0",
      "Total Revenue": "209194900000.0",
      "Operating Revenue": "209194900000.0"
    },
    "2024-09-30": {
      "Tax Effect Of Unusual Items": "0.0",
      "Tax Rate For Calcs": "0.192692",
      "Total Unusual Items": "0.0",
      "Total Unusual Items Excluding Goodwill": "0.0",
      "Net Income From Continuing Operation Net Minority Interest": "74012600000.0",
      "Net Interest Income": "139861300000.0",
      "Interest Expense": "176149200000.0",
      "Interest Income": "316010500000.0",
      "Normalized Income": "74012600000.0",
      "Net Income From Continuing And Discontinued Operation": "74012600000.0",
      "Diluted Average Shares": "3112388562.0",
      "Basic Average Shares": "3091587302.0",
      "Diluted EPS": "23.78",
      "Basic EPS": "23.94",
      "Diluted NI Availto Com Stockholders": "74012600000.0",
      "Net Income Common Stockholders": "74012600000.0",
      "Net Income": "74012600000.0",
      "Minority Interests": "-344000000.0",
      "Net Income Including Noncontrolling Interests": "74356600000.0",
      "Net Income Extraordinary": "0.0",
      "Net Income Continuous Operations": "74356600000.0",
      "Tax Provision": "17683900000.0",
      "Pretax Income": "91772900000.0",
      "Special Income Charges": "0.0",
      "Operating Expense": "101369800000.0",
      "Other Operating Expenses": "66641400000.0",
      "Total Revenue": "215888500000.0",
      "Operating Revenue": "215888500000.0"
    },
    "2024-06-30": {
      "Tax Effect Of Unusual Items": "0.0",
      "Tax Rate For Calcs": "0.253757",
      "Total Unusual Items": "0.0",
      "Total Unusual Items Excluding Goodwill": "0.0",
      "Net Income From Continuing Operation Net Minority Interest": "64364300000.0",
      "Net Interest Income": "138975200000.0",
      "Interest Expense": "172610000000.0",
      "Interest Income": "311585200000.0",
      "Normalized Income": "64364300000.0",
      "Net Income From Continuing And Discontinued Operation": "64364300000.0",
      "Diluted Average Shares": "3110889319.0",
      "Basic Average Shares": "3088498081.0",
      "Diluted EPS": "20.69",
      "Basic EPS": "20.84",
      "Diluted NI Availto Com Stockholders": "64364300000.0",
      "Net Income Common Stockholders": "64364300000.0",
      "Net Income": "64364300000.0",
      "Minority Interests": "-307000000.0",
      "Net Income Including Noncontrolling Interests": "64671300000.0",
      "Net Income Extraordinary": "0.0",
      "Net Income Continuous Operations": "64671300000.0",
      "Tax Provision": "21933100000.0",
      "Pretax Income": "86433400000.0",
      "Special Income Charges": "0.0",
      "Operating Expense": "97900300000.0",
      "Other Operating Expenses": "62954100000.0",
      "Total Revenue": "205348800000.0",
      "Operating Revenue": "205348800000.0"
    },
    "2024-03-31": {
      "Tax Effect Of Unusual Items": "624673430.500347",
      "Tax Rate For Calcs": "0.237491",
      "Total Unusual Items": "2630300000.0",
      "Total Unusual Items Excluding Goodwill": "2630300000.0",
      "Net Income From Continuing Operation Net Minority Interest": "75990400000.0",
      "Net Interest Income": "135033400000.0",
      "Interest Expense": "167272400000.0",
      "Interest Income": "302305800000.0",
      "Normalized Income": "73984773430.50035",
      "Net Income From Continuing And Discontinued Operation": "75990400000.0",
      "Diluted Average Shares": "0.0",
      "Basic Average Shares": "0.0",
      "Diluted EPS": "0.0",
      "Basic EPS": "0.0",
      "Diluted NI Availto Com Stockholders": "75990400000.0",
      "Net Income Common Stockholders": "75990400000.0",
      "Net Income": "75990400000.0",
      "Minority Interests": "-310300000.0",
      "Net Income Including Noncontrolling Interests": "76300700000.0",
      "Net Income Extraordinary": "0.0",
      "Net Income Continuous Operations": "76300700000.0",
      "Tax Provision": "23713200000.0",
      "Pretax Income": "99848700000.0",
      "Special Income Charges": "2630300000.0",
      "Operating Expense": "103484100000.0",
      "Other Operating Expenses": "18521700000.0",
      "Total Revenue": "211132800000.0",
      "Operating Revenue": "211132800000.0"
    },
    "2023-12-31": {
      "Tax Effect Of Unusual Items": "0.0",
      "Tax Rate For Calcs": "0.0",
      "Total Unusual Items": "0.0",
      "Total Unusual Items Excluding Goodwill": "0.0",
      "Net Income From Continuing Operation Net Minority Interest": "0.0",
      "Net Interest Income": "0.0",
      "Interest Expense": "0.0",
      "Interest Income": "0.0",
      "Normalized Income": "0.0",
      "Net Income From Continuing And Discontinued Operation": "0.0",
      "Diluted Average Shares": "3101605351.0",
      "Basic Average Shares": "3082459639.0",
      "Diluted EPS": "20.93",
      "Basic EPS": "21.06",
      "Diluted NI Availto Com Stockholders": "0.0",
      "Net Income Common Stockholders": "0.0",
      "Net Income": "0.0",
      "Minority Interests": "0.0",
      "Net Income Including Noncontrolling Interests": "0.0",
      "Net Income Extraordinary": "0.0",
      "Net Income Continuous Operations": "0.0",
      "Tax Provision": "0.0",
      "Pretax Income": "0.0",
      "Special Income Charges": "0.0",
      "Operating Expense": "0.0",
      "Other Operating Expenses": "0.0",
      "Total Revenue": "0.0",
      "Operating Revenue": "0.0"
    },
    "2023-09-30": {
      "Tax Effect Of Unusual Items": "0.0",
      "Tax Rate For Calcs": "0.0",
      "Total Unusual Items": "0.0",
      "Total Unusual Items Excluding Goodwill": "0.0",
      "Net Income From Continuing Operation Net Minority Interest": "0.0",
      "Net Interest Income": "0.0",
      "Interest Expense": "0.0",
      "Interest Income": "0.0",
      "Normalized Income": "0.0",
      "Net Income From Continuing And Discontinued Operation": "0.0",
      "Diluted Average Shares": "3098976024.0",
      "Basic Average Shares": "3080511420.0",
      "Diluted EPS": "20.02",
      "Basic EPS": "20.14",
      "Diluted NI Availto Com Stockholders": "0.0",
      "Net Income Common Stockholders": "0.0",
      "Net Income": "0.0",
      "Minority Interests": "0.0",
      "Net Income Including Noncontrolling Interests": "0.0",
      "Net Income Extraordinary": "0.0",
      "Net Income Continuous Operations": "0.0",
      "Tax Provision": "0.0",
      "Pretax Income": "0.0",
      "Special Income Charges": "0.0",
      "Operating Expense": "0.0",
      "Other Operating Expenses": "0.0",
      "Total Revenue": "0.0",
      "Operating Revenue": "0.0"
    }
  },
  "cashflow": {}
}