{"query": "BPCL CMD Post – Final Selection Panel Imminent", "similar": [{"title": "BPCL divestiture not on cards, says Central Government", "date": "2022-09-15 07:42:00.000", "impact": "-5.08%"}, {"title": "BPCL Board Approves Stake Sale In Numaligarh Refinery; What Should Investors Do?", "date": "2021-03-02 09:55:02.000", "impact": "+1.27%"}, {"title": "BPCL divestment: Govt may take a fresh look, says official", "date": "2022-04-21 17:30:00.000", "impact": "+3.80%"}]}
{"query": "1st-ever BONUS announcement by top PSU; BPCL and GAIL are promoters", "similar": [{"title": "Power Grid, Godrej Properties, Indian Bank in spotlight", "date": "2021-06-11 08:39:00.000", "impact": "+0.58%"}, {"title": "Indian Oil Recommends Issue of Bonus Shares; Know Record Date, Share Ratio, Other Details", "date": "2022-06-24 12:05:42.000", "impact": "+1.17%"}, {"title": "Air Products starts supplying syngas to BPCL-Kochi Refinery", "date": "2021-04-20 14:39:05.000", "impact": "+4.46%"}]}
