{"query": "L&T Finance Holdings gets Board nod for raising up to ₹1.01 lakh crore via NCDs in 1 or more tranches", "similar": [{"title": "Adani Ports & SEZ raises Rs 1,000 crore through non-convertible debentures", "date": "2021-10-19 00:25:00.000", "impact": "-0.82%"}, {"title": "NTPC gains on plan to raise Rs 500 cr via NCDs", "date": "2022-12-14 17:04:08.000", "impact": "+1.21%"}, {"title": "SBI Card board to mull fund raising on 12 March", "date": "2021-03-08 13:31:00", "impact": "+2.44%"}]}
