{
  "decision": "HOLD",
  "confidence": 6,
  "volatility": 16.37,
  "sharpe_ratio": -0.29,
  "reasoning": "The stock's recent performance has been disappointing, with a negative return and high volatility. However, the company's financial health is stable, with strong profitability and attractive valuation. The news sentiment is neutral to positive, with a focus on fundraising plans, which could lead to an influx of capital. Given the mixed signals, I would hold the stock for now, awaiting more clarity on the fundraising strategy and Q4 results."
}