{
  "decision": "BUY",
  "confidence": 8,
  "volatility": 37.54,
  "sharpe_ratio": 0.50,
  "reasoning": "The stock has shown strong weekly performance with a 4.71% return, outperforming its peers. The company's fundamentals are strong, with high ROE and decent profit margins, indicating a stable business. The positive news sentiment, with a 'BUY' recommendation from BNP Paribas, suggests a potential upside for the stock. Although the valuation is on the higher side, the overall macroeconomic environment is supportive, with a growing services sector and easing inflation, which could drive the stock's growth."
}