{
  "decision": "HOLD",
  "confidence": 6,
  "volatility": 21.67,
  "sharpe_ratio": -0.81,
  "reasoning": "The stock's poor performance this week, with a return of -4.37% and a high volatility of 21.67%, suggests caution. However, the company's strong fundamentals, including high ROE and profit margins, and impressive revenue and earnings growth rates, offset its high valuation and debt position. In the current macroeconomic environment, with a growing services sector and improving employment numbers, the stock's prospects are not entirely bleak. Therefore, a HOLD decision is warranted, pending further evaluation."
}