{
  "decision": "HOLD",
  "confidence": 6,
  "volatility": 13.9,
  "sharpe_ratio": -0.37,
  "reasoning": "ICICIBANK's weekly performance was relatively resilient, but its volatility remained elevated, indicating a moderate level of risk. The company's fundamentals are strong, with a high profit margin and decent ROE, but its valuation seems rich. The news sentiment is neutral to positive, and the macroeconomic environment is supportive of the banking sector. However, the stock's high volatility and rich valuation make me cautious, leading me to hold the stock for now."
}