{
  "decision": "HOLD",
  "confidence": 7,
  "volatility": 26.18,
  "sharpe_ratio": 0.48,
  "reasoning": "The stock has a strong weekly return of 3.15%, outperforming its peers, but its high volatility of 26.18% is a concern. The company's fundamentals are mixed, with strong ROE and gross margins, but a high debt-to-equity ratio and trailing P/E ratio. The news sentiment is neutral, and the macroeconomic environment is generally positive, with growth in agriculture, services, and manufacturing sectors. Overall, the stock's strong return is somewhat justified by its risk-taking, but investors should be cautious of its high volatility."
}