{
  "decision": "HOLD",
  "confidence": 7,
  "volatility": 0.0,
  "sharpe_ratio": 1728.64,
  "reasoning": "ITC's weekly performance was characterized by low risk and modest returns. The company's financial health is strong, with a strong profitability profile and promising growth metrics. However, the revenue growth rate is relatively low. Given the stable performance and reasonable valuation, I would recommend holding the stock for now, but closely monitoring its revenue growth and macroeconomic environment."
}