{
  "decision": "HOLD",
  "confidence": 6,
  "volatility": 15.42,
  "sharpe_ratio": 0.60,
  "reasoning": "The stock's weekly return of 2.35% is relatively strong, driven by moderate volatility. However, the company's financial health appears mixed, with undervaluation and decent profitability offset by declining revenue and earnings growth, and high debt levels. The news sentiment is neutral, and the macroeconomic environment is stable, but not exceptionally strong. Therefore, I recommend a HOLD decision, as the stock's performance is decent but not outstanding, and there are concerns about its growth prospects."
}