{
  "decision": "HOLD",
  "confidence": 7,
  "volatility": 25.56,
  "sharpe_ratio": 0.91,
  "reasoning": "NTPC's strong weekly performance and decent fundamentals, including a reasonable valuation and moderate revenue and earnings growth, suggest a HOLD decision. However, the high debt-to-equity ratio and mixed news sentiment temper my confidence. The macroeconomic environment, with a growing services sector and stable interest rates, provides a supportive backdrop, but I would like to see debt reduction efforts before becoming more bullish."
}