{
  "decision": "HOLD",
  "confidence": 6,
  "volatility": 29.14,
  "sharpe_ratio": 0.53,
  "reasoning": "The stock has a strong weekly performance, outperforming its peers, but its high volatility and stretched valuation are concerns. The company's financial health is stable, but the debt-to-equity ratio is high. The news sentiment is neutral to positive, and the macroeconomic environment is stable, but not exceptionally strong. Overall, it's a HOLD decision, as the stock's strong performance is somewhat offset by its valuation and debt concerns."
}